{"label": "Gift Hampers and Baskets", "description": "Market category for gift hampers and baskets, including food, drink, and pampering items.", "intents": ["Find gift ideas for special occasions", "Send a thoughtful gift to a loved one", "Order a hamper for a corporate event"], "subcategories": [{"label": "Food Hampers", "relevance": 0.8, "description": "Hampers filled with gourmet food items.", "nouns": ["Cheese", "Wine", "Chocolate", "Fruit", "Meat"], "subtopics": ["Cheese and Wine Hampers", "Chocolate Hampers", "Fruit Baskets", "Meat Hampers"]}, {"label": "Pamper Hampers", "relevance": 0.6, "description": "Hampers filled with beauty and self-care items.", "nouns": ["Bath", "Candles", "Skincare", "Perfume", "Makeup"], "subtopics": ["Bath and Body Hampers", "Candle Hampers", "Skincare Hampers", "Perfume Hampers"]}, {"label": "Alcohol Hampers", "relevance": 0.5, "description": "Hampers filled with alcoholic beverages.", "nouns": ["Wine", "Champagne", "Beer", "Spirits", "Cocktails"], "subtopics": ["Wine and Cheese Hampers", "Champagne and Chocolate Hampers", "Beer Hampers", "Spirits Hampers"]}, {"label": "Corporate Hampers", "relevance": 0.4, "description": "Hampers designed for corporate gifting.", "nouns": ["Branded", "Bulk", "Customizable", "Luxury", "Executive"], "subtopics": ["Branded Hampers", "Bulk Hampers", "Customizable Hampers", "Luxury Hampers"]}, {"label": "Fruit Bouquets", "relevance": 0.3, "description": "Arrangements of fruit arranged like a bouquet.", "nouns": ["Fruit", "Flowers", "Chocolate", "Dipped", "Edible"], "subtopics": ["Chocolate Dipped Fruit Bouquets", "Edible Flower Bouquets", "Fruit and Cheese Hampers"]}]}