{"label": "Cleaning and Hygiene Supplies", "description": "Products and services related to cleaning and hygiene, including equipment, tools, and supplies.", "intents": ["Find cleaning supplies for home or office", "Rent or buy cleaning equipment", "Get professional cleaning services", "Find hygiene products for personal or commercial use"], "subcategories": [{"label": "Cleaning Equipment", "relevance": 0.9, "description": "Machines and tools used for cleaning floors, carpets, windows, and other surfaces.", "nouns": ["Carpet cleaner", "Pressure washer", "Steam mop", "Window scraper", "Polishing machine", "Floor buffer", "Vacuum cleaner", "Wet and dry vacuum", "Spin mop", "Wonder broom"], "subtopics": ["Carpet cleaning", "Window cleaning", "Floor cleaning", "Pressure washing", "Vacuuming"]}, {"label": "Cleaning Supplies", "relevance": 0.8, "description": "Products used for cleaning surfaces, including chemicals, cloths, and mops.", "nouns": ["Mop", "Bucket", "Dustpan", "Brush", "Squeegee", "Spray mop", "Flash mop", "Swiffer mop", "Clever mop", "Mop slippers"], "subtopics": ["Floor cleaning", "Kitchen cleaning", "Bathroom cleaning", "Window cleaning", "Car cleaning"]}, {"label": "Hygiene Products", "relevance": 0.7, "description": "Products used for personal or commercial hygiene, including soap dispensers, air dryers, and urinals.", "nouns": ["Soap dispenser", "Air dryer", "Urinal", "Toilet cubicles", "Hand dryer", "Post poo drops", "Portable urinal", "Under sink bin", "Shower gel dispenser", "Toilet flush system"], "subtopics": ["Hand hygiene", "Bathroom hygiene", "Commercial hygiene", "Personal hygiene", "Odor control"]}, {"label": "Waste Management", "relevance": 0.6, "description": "Products and services related to waste disposal and recycling, including bins, bags, and incinerators.", "nouns": ["Bin", "Wheelie bin", "Bin bag", "Incinerator bin", "Recycling bin", "Dustbin", "Metal bin", "Plastic dustbin", "Slimline kitchen bin", "Outdoor bin"], "subtopics": ["Household waste", "Commercial waste", "Recycling", "Hazardous waste", "Medical waste"]}, {"label": "Janitorial Supplies", "relevance": 0.5, "description": "Products and services used by janitors and cleaning professionals, including gloves, masks, and cleaning carts.", "nouns": ["Gloves", "Masks", "Cleaning cart", "Janitorial trolley", "Cleaning trolley", "Mops and brooms", "Industrial vacuum", "Janitorial supplies", "Cleaning laminate floors", "Floor mop"], "subtopics": ["Cleaning tools", "Personal protective equipment", "Cleaning chemicals", "Cleaning carts", "Janitorial services"]}]}