{"label": "Drawing Instruments and Supplies", "description": "Tools and materials used for drawing and technical illustration.", "intents": ["Find high-quality drawing instruments", "Purchase drawing supplies", "Learn about technical drawing tools"], "subcategories": [{"label": "Drawing Boards", "relevance": 0.8, "description": "Flat surfaces used for drawing and drafting.", "nouns": ["Blundell Harling", "Ergo Soft", "Walton", "A2", "A3", "A4", "Wooden", "Adjustable", "Desktop", "Portable"], "subtopics": ["Adjustable angle", "With parallel motion", "With stand"]}, {"label": "Drawing Tools", "relevance": 0.7, "description": "Instruments used for drawing and technical illustration.", "nouns": ["Compass", "Protractor", "Set square", "Ruler", "Mechanical pencil", "Technical pen", "Fineliner", "Eraser", "Light box", "Tracing paper"], "subtopics": ["Geometry", "Circle drawing", "Angle measurement"]}, {"label": "Pencils", "relevance": 0.6, "description": "Writing instruments used for drawing and sketching.", "nouns": ["Staedtler Noris", "Ergo Soft", "Mars Lumograph", "Aquarell", "Karat", "Colored", "Triangular", "HB", "2B", "4B"], "subtopics": ["Watercolor", "Coloring", "Sketching"]}, {"label": "Light Tables", "relevance": 0.5, "description": "Backlit surfaces used for tracing and drawing.", "nouns": ["A4", "A3", "A2", "Cube", "LED", "Portable", "Tabletop", "Drawing board", "Light pad", "Animation"], "subtopics": ["Tracing", "Animation", "Drawing"]}, {"label": "Easels", "relevance": 0.4, "description": "Stands used to hold drawing boards or canvases.", "nouns": ["Jakar", "Aluminium", "Wooden", "Tabletop", "Adjustable", "Portable", "Drawing table", "Artist", "Lightweight", "Children"], "subtopics": ["Tabletop", "Adjustable angle", "Portable"]}]}