{"label": "Entertainment and Hobbies", "description": "Search queries related to entertainment and hobbies, including musical instruments, books, shows, and games.", "intents": ["Find tickets for shows and musicals", "Learn to play a musical instrument", "Buy books and audio books", "Find games and toys"], "subcategories": [{"label": "Musical Instruments", "relevance": 0.8, "description": "Search queries related to buying and learning to play musical instruments.", "nouns": ["guitar", "piano", "violin", "sax", "drum kit", "microphone", "trombone", "french horn", "cello", "trumpet"], "subtopics": ["Acoustic guitars", "Electric guitars", "Piano lessons", "Violin accessories", "Drum kits", "Microphone stands", "Brass instruments", "String instruments", "Woodwind instruments", "Music production equipment"]}, {"label": "Books and Audio Books", "relevance": 0.7, "description": "Search queries related to buying and downloading books and audio books.", "nouns": ["books", "audio books", "true story", "dork diaries", "goosebumps", "beast quest", "lee child", "julia donaldson", "the gruffalo", "elizabeth is missing"], "subtopics": ["Fiction books", "Non-fiction books", "Children's books", "Audio books", "Bestsellers", "Biographies", "Self-help books", "Mystery and thriller books", "Romance books", "Science fiction and fantasy books"]}, {"label": "Shows and Musicals", "relevance": 0.6, "description": "Search queries related to buying tickets for shows and musicals.", "nouns": ["shows", "musicals", "lion king", "matilda", "motown", "book of mormon", "phantom of the opera", "carole king", "betty boop", "the bodyguard"], "subtopics": ["West End shows", "Broadway shows", "Musicals in London", "Children's shows", "Drama shows", "Comedy shows", "Romantic shows", "Classic shows", "New shows", "Off-Broadway shows"]}, {"label": "Games and Toys", "relevance": 0.5, "description": "Search queries related to buying games and toys.", "nouns": ["board games", "video games", "toys", "magic 8 ball", "dart board", "hover shot", "zorbing", "etch a sketch", "foosball", "message in a bottle"], "subtopics": ["Board games", "Video games", "Outdoor toys", "Indoor toys", "Educational toys", "Action figures", "Building toys", "Puzzles", "Card games", "Party games"]}]}