{"label": "Postal and Delivery Services", "description": "Services related to sending and receiving packages and mail.", "intents": ["Send a package", "Track a package", "Find a courier service", "Get a PO box", "Forward mail"], "subcategories": [{"label": "Domestic Parcel Delivery", "relevance": 0.8, "description": "Delivery of packages within the same country.", "nouns": ["Courier", "Parcel", "Delivery", "Collection", "Postage"], "subtopics": ["Next-day delivery", "Large parcel delivery", "Parcel tracking", "Parcel comparison", "Parcel collection"]}, {"label": "International Parcel Delivery", "relevance": 0.7, "description": "Delivery of packages to other countries.", "nouns": ["International", "Courier", "Parcel", "Delivery", "Postage"], "subtopics": ["Customs clearance", "International tracking", "Air freight", "Sea freight", "Parcel comparison"]}, {"label": "PO Boxes and Mail Forwarding", "relevance": 0.6, "description": "Services related to receiving mail at a different address.", "nouns": ["PO box", "Mail forwarding", "Address verification", "Mailbox", "Post office"], "subtopics": ["Virtual mailbox", "Mail scanning", "Mail holding", "Mail redirection", "Mailbox rental"]}, {"label": "Office and Business Services", "relevance": 0.5, "description": "Services related to office and business needs.", "nouns": ["Registered office", "Address service", "Business address", "Courier", "Delivery"], "subtopics": ["Virtual office", "Mailroom management", "Document storage", "Document shredding", "Office supplies"]}, {"label": "Christmas and Seasonal Jobs", "relevance": 0.4, "description": "Temporary jobs related to the holiday season.", "nouns": ["Christmas jobs", "Seasonal jobs", "Temporary jobs", "Job vacancies", "Employment"], "subtopics": ["Retail jobs", "Delivery jobs", "Warehouse jobs", "Customer service jobs", "Hospitality jobs"]}]}