{"label": "Entertainment Merchandise", "description": "Merchandise related to popular movies, TV shows, and comics.", "intents": ["Purchase merchandise related to favorite movies and TV shows", "Find collectibles and memorabilia from popular franchises", "Gifts for fans of popular movies and TV shows"], "subcategories": [{"label": "Superhero Merchandise", "relevance": 0.8, "description": "Merchandise related to popular superhero franchises.", "nouns": ["Avengers", "Batman", "Superman", "Spiderman", "Captain America", "Iron Man", "Hulk", "Thor", "Black Panther", "Ant Man"], "subtopics": ["Action figures", "Costumes", "Collectibles", "Comics", "Posters"]}, {"label": "Movie and TV Show Merchandise", "relevance": 0.7, "description": "Merchandise related to popular movies and TV shows.", "nouns": ["Star Wars", "Harry Potter", "Lord of the Rings", "Jurassic Park", "Mad Max", "James Bond", "Indiana Jones", "Pirates of the Caribbean", "Mission Impossible", "Fast and Furious"], "subtopics": ["Action figures", "Costumes", "Collectibles", "Posters", "DVDs and Blu-rays"]}, {"label": "Martial Arts Merchandise", "relevance": 0.4, "description": "Merchandise related to martial arts movies and TV shows.", "nouns": ["Bruce Lee", "Karate Kid", "Ip Man", "Van Damme", "Jackie Chan", "Kung Fu Panda", "Nunchucks", "Talismans", "Yellow Jumpsuit", "Ninjas"], "subtopics": ["Action figures", "Costumes", "Collectibles", "Posters", "DVDs and Blu-rays"]}, {"label": "Gaming Merchandise", "relevance": 0.3, "description": "Merchandise related to popular video games.", "nouns": ["Spiderman", "Assassin's Creed", "Tomb Raider", "Batman Arkham", "Until Dawn", "Deadpool", "Hitman", "Watchmen", "Daredevil", "Captain America Civil War"], "subtopics": ["Action figures", "Costumes", "Collectibles", "Posters", "Video game accessories"]}]}