{"label": "Fitness Equipment", "description": "Equipment and accessories for home and gym workouts.", "intents": ["Build muscle", "Lose weight", "Improve fitness", "Train for a specific sport", "Rehabilitate an injury"], "entities": ["Fitbit", "Reebok", "York", "ProForm", "Slendertone", "Wolverson", "Concept 2", "NordicTrack"], "subcategories": [{"label": "Cardio Equipment", "relevance": 0.8, "description": "Equipment for aerobic exercise and cardiovascular health.", "nouns": ["Treadmill", "Exercise bike", "Rowing machine", "Elliptical", "Vibration plate", "Trampoline"], "subtopics": ["Manual vs motorized treadmills", "Upright vs recumbent bikes", "Air vs magnetic rowers", "Front vs rear drive ellipticals", "Benefits of vibration plates", "Indoor vs outdoor trampolines"]}, {"label": "Strength Training Equipment", "relevance": 0.7, "description": "Equipment for building muscle and increasing strength.", "nouns": ["Dumbbells", "Kettlebells", "Barbells", "Weight plates", "Weight benches", "Power racks"], "subtopics": ["Free weights vs machines", "Adjustable vs fixed dumbbells", "Cast iron vs vinyl weights", "Flat vs incline vs decline benches", "Squat vs power racks", "Benefits of kettlebell swings"]}, {"label": "Functional Training Equipment", "relevance": 0.6, "description": "Equipment for improving balance, coordination, and flexibility.", "nouns": ["Resistance bands", "Suspension trainers", "Balance boards", "Foam rollers", "Pilates mats", "Yoga blocks"], "subtopics": ["Benefits of resistance band exercises", "TRX vs Jungle Gym suspension trainers", "Benefits of balance board exercises", "Benefits of foam rolling", "Benefits of Pilates", "Benefits of yoga"]}, {"label": "Accessories", "relevance": 0.5, "description": "Accessories for enhancing workouts and preventing injuries.", "nouns": ["Fitness trackers", "Gym gloves", "Resistance tubes", "Foam pads", "Skipping ropes", "Ab wheels"], "subtopics": ["Benefits of fitness tracking", "Benefits of gym gloves", "Benefits of resistance tube exercises", "Benefits of foam pads for knees and elbows", "Benefits of skipping rope exercises", "Benefits of ab wheel exercises"]}]}