{"label": "Musical Theater", "description": "Performing arts productions that combine singing, dancing, and acting to tell a story.", "intents": ["Find tickets to musicals", "Buy costumes for musicals", "Listen to soundtracks from musicals"], "subcategories": [{"label": "Grease", "relevance": 0.8, "description": "A popular musical set in the 1950s that follows the romantic relationship between two high school students.", "nouns": ["Sandy", "Danny", "Pink Ladies", "T-Birds", "Rydell High"], "subtopics": ["Grease costumes", "Grease soundtrack", "Grease tickets"]}, {"label": "Mary Poppins", "relevance": 0.6, "description": "A classic musical about a magical nanny who helps a family in London.", "nouns": ["Bert", "Chimney sweep", "Carpet bag", "Practically perfect"], "subtopics": ["Mary Poppins costumes", "Mary Poppins soundtrack", "Mary Poppins tickets"]}, {"label": "Phantom of the Opera", "relevance": 0.5, "description": "A gothic romance musical about a mysterious figure who haunts the Paris Opera House.", "nouns": ["Christine", "Mask", "Music box", "Opera"], "subtopics": ["Phantom of the Opera tickets", "Phantom of the Opera soundtrack", "Phantom of the Opera merchandise"]}, {"label": "Moulin Rouge", "relevance": 0.4, "description": "A musical set in Paris in the early 1900s that follows a young writer who falls in love with a cabaret actress.", "nouns": ["Can-can", "Show", "Costumes", "Paris"], "subtopics": ["Moulin Rouge tickets", "Moulin Rouge soundtrack", "Moulin Rouge merchandise"]}, {"label": "Les Miserables", "relevance": 0.3, "description": "A musical set in 19th century France that follows the story of Jean Valjean, a former convict who seeks redemption.", "nouns": ["Revolution", "Barricades", "Cosette", "Javert"], "subtopics": ["Les Miserables tickets", "Les Miserables soundtrack", "Les Miserables merchandise"]}]}