{"label": "Panasonic TVs and Sustainable Building", "description": "Market category encompassing search queries related to Panasonic TVs and sustainable building ideas.", "intents": ["Find information about Panasonic TVs", "Learn about sustainable building ideas", "Find project management consultancy services", "Find regulatory consultants", "Find energy consulting firms", "Find business consultants"], "subcategories": [{"label": "Panasonic TVs", "relevance": 0.8, "description": "Subcategory encompassing search queries related to Panasonic TVs.", "nouns": ["Panasonic", "TVs"], "subtopics": ["TV models", "TV stands", "TV reviews"]}, {"label": "Sustainable Building", "relevance": 0.7, "description": "Subcategory encompassing search queries related to sustainable building ideas.", "nouns": ["sustainable building", "compost toilet", "retrofit passive house", "energy saving materials", "green roof", "rainwater harvesting", "leed insulation", "environmental sustainability", "energy efficiency", "air tightness testing"], "subtopics": ["Building materials", "Composting toilets", "Passive houses"]}, {"label": "Consultancy Services", "relevance": 0.6, "description": "Subcategory encompassing search queries related to consultancy services.", "nouns": ["project management", "regulatory consultants", "energy consulting firms", "business consultants", "cost reduction consultants", "online business consultant", "business change consultant", "recruitment consultant", "strategic branding consultancy", "business analysis consulting"], "subtopics": ["Project management", "Regulatory compliance", "Energy consulting", "Business consulting"]}]}