{"label": "Electronics Retail", "description": "Retailers of electronic devices and accessories.", "intents": ["Purchase electronic devices and accessories", "Compare prices of electronic devices and accessories", "Find reviews of electronic devices and accessories"], "subcategories": [{"label": "Laptops", "relevance": 0.9, "description": "Portable computers for personal and professional use.", "nouns": ["HP Pavilion", "Sony Vaio", "Dell Inspiron", "Lenovo Thinkpad", "Apple MacBook"], "subtopics": ["Gaming laptops", "Budget laptops", "Laptops on finance"]}, {"label": "Tablets", "relevance": 0.8, "description": "Portable touchscreen devices for personal and professional use.", "nouns": ["iPad", "Samsung Galaxy Tab", "Amazon Fire", "Asus Tablet", "Microsoft Surface"], "subtopics": ["10 inch tablets", "Tablet stands", "Tablets on finance"]}, {"label": "Headphones", "relevance": 0.7, "description": "Audio devices worn over the ears or in the ear canal.", "nouns": ["Bose QuietComfort", "Sony MDR", "Sennheiser Momentum", "Skullcandy Hesh", "Beats Solo"], "subtopics": ["Wireless headphones", "Noise-cancelling headphones", "Earbuds"]}, {"label": "Speakers", "relevance": 0.6, "description": "Devices that produce sound for personal or professional use.", "nouns": ["Sonos Play", "LG Soundbar", "Bose SoundTrue", "JBL Flip", "Bluetooth speakers"], "subtopics": ["Wireless speakers", "Portable speakers", "Home theater speakers"]}, {"label": "Accessories", "relevance": 0.5, "description": "Additional devices or items that enhance the functionality of electronic devices.", "nouns": ["Micro SD card", "VPN service", "PowerPoint templates", "OTG cable", "Flash drive"], "subtopics": ["Laptop accessories", "Tablet accessories", "Headphone accessories"]}]}