{"label": "Superhero Merchandise", "description": "Merchandise related to comic book superheroes and their franchises.", "intents": ["Purchase superhero-themed products", "Find superhero collectibles", "Explore superhero merchandise options"], "subcategories": [{"label": "Comic Books", "relevance": 0.9, "description": "Printed or digital publications featuring superhero stories and characters.", "nouns": ["Comics", "Graphic novels", "Manga", "Volumes", "Issues"], "subtopics": ["Marvel Comics", "DC Comics", "Image Comics"]}, {"label": "Action Figures", "relevance": 0.8, "description": "Posable figurines of superhero characters.", "nouns": ["Figures", "Toys", "Collectibles"], "subtopics": ["Marvel Legends", "DC Multiverse", "Funko Pop"]}, {"label": "Clothing and Accessories", "relevance": 0.7, "description": "Apparel and items worn or used by superhero fans.", "nouns": ["T-shirts", "Hoodies", "Masks", "Jewelry", "Socks"], "subtopics": ["Superhero costumes", "Cosplay accessories", "Superhero-themed socks"]}, {"label": "Video Games", "relevance": 0.6, "description": "Interactive entertainment featuring superhero characters and stories.", "nouns": ["Games", "Consoles", "Accessories"], "subtopics": ["Marvel's Spider-Man", "Batman: Arkham", "LEGO Marvel Super Heroes"]}, {"label": "Movies and TV Shows", "relevance": 0.5, "description": "Films and television series featuring superhero characters and stories.", "nouns": ["Movies", "TV shows", "Blu-rays", "DVDs"], "subtopics": ["Marvel Cinematic Universe", "DC Extended Universe", "The Walking Dead"]}]}