{"label": "Gift Wrapping Supplies", "description": "Supplies for wrapping gifts, including wrapping paper, ribbons, bows, and gift bags.", "intents": ["Find wrapping paper for a birthday gift", "Buy ribbons for gift wrapping", "Purchase gift bags for Christmas presents"], "subcategories": [{"label": "Wrapping Paper", "relevance": 0.9, "description": "Paper used to wrap gifts.", "nouns": ["Christmas wrapping paper", "Personalized wrapping paper", "Recycled wrapping paper"], "subtopics": ["Christmas wrapping paper", "Personalized wrapping paper", "Recycled wrapping paper"]}, {"label": "Ribbons and Bows", "relevance": 0.8, "description": "Decorative ribbons and bows used to adorn gifts.", "nouns": ["Satin ribbon", "Personalized ribbon", "Velvet ribbon"], "subtopics": ["Satin ribbon", "Personalized ribbon", "Velvet ribbon"]}, {"label": "Gift Bags", "relevance": 0.7, "description": "Bags used to hold gifts.", "nouns": ["Christmas gift bags", "Personalized gift bags", "Small gift bags"], "subtopics": ["Christmas gift bags", "Personalized gift bags", "Small gift bags"]}, {"label": "Cellophane and Clear Wrap", "relevance": 0.6, "description": "Clear wrapping materials used to wrap gifts.", "nouns": ["Clear cellophane", "Clear wrapping paper", "Clear cellophane bags"], "subtopics": ["Clear cellophane", "Clear wrapping paper", "Clear cellophane bags"]}, {"label": "Gift Boxes", "relevance": 0.5, "description": "Boxes used to hold gifts.", "nouns": ["Christmas gift boxes", "Personalized gift boxes", "Small gift boxes"], "subtopics": ["Christmas gift boxes", "Personalized gift boxes", "Small gift boxes"]}]}