{"label": "Home Appliances", "description": "Market category for home appliances and repair services.", "intents": ["Find repair services for home appliances", "Buy new home appliances", "Find replacement parts for home appliances"], "subcategories": [{"label": "Washing Machines", "relevance": 0.9, "description": "Home appliances used for washing clothes.", "nouns": ["Washing machine", "Repairs", "Parts", "Service", "Pump", "Bearing", "Tap", "Extension hose", "Y piece", "Moving"], "subtopics": ["Repairs", "Parts", "Service"]}, {"label": "Refrigerators", "relevance": 0.8, "description": "Home appliances used for storing food and drinks.", "nouns": ["Refrigerator", "Fridge", "Freezer", "Repairs", "Parts", "Service", "Compressor", "Shelves", "Ice dispenser", "Water dispenser"], "subtopics": ["Repairs", "Parts", "Service"]}, {"label": "Dishwashers", "relevance": 0.7, "description": "Home appliances used for washing dishes.", "nouns": ["Dishwasher", "Repairs", "Parts", "Service", "Inlet hose", "Extension hose", "Filter", "Inlet valve", "Engineer", "Hose"], "subtopics": ["Repairs", "Parts", "Service"]}, {"label": "Ovens", "relevance": 0.6, "description": "Home appliances used for cooking food.", "nouns": ["Oven", "Repairs", "Parts", "Service", "Knob", "Element", "Thermostat", "Timer", "Fixers", "Gas"], "subtopics": ["Repairs", "Parts", "Service"]}, {"label": "Dryers", "relevance": 0.5, "description": "Home appliances used for drying clothes.", "nouns": ["Dryer", "Repairs", "Parts", "Service", "Hose", "Filter", "Problems", "Tumble", "Handle", "Hoover"], "subtopics": ["Repairs", "Parts", "Service"]}]}