{"label": "Kitchen Appliances and Cookware", "description": "Products and accessories for cooking and food preparation.", "intents": ["Find kitchen appliances", "Buy cookware", "Compare prices", "Get product reviews"], "subcategories": [{"label": "Microwaves", "relevance": 0.9, "description": "Small electric ovens used for heating and cooking food.", "nouns": ["Flatbed microwave", "Cream microwave", "Silver microwave", "Retro microwave", "Amazon microwave", "Small microwave", "Samsung microwave"], "subtopics": ["Microwave ovens", "Microwave features", "Microwave brands"]}, {"label": "Cookers", "relevance": 0.8, "description": "Appliances used for cooking food, including gas and electric models.", "nouns": ["Cannon cookers", "Leisure cookers", "Gas cooker sale", "Currys gas hobs", "Currys cookers", "Electric range cookers", "Freestanding electric cooker"], "subtopics": ["Gas cookers", "Electric cookers", "Cooker features"]}, {"label": "Coffee and Tea", "relevance": 0.7, "description": "Appliances and accessories for making coffee and tea.", "nouns": ["Nespresso pods", "Krups", "Cafetiere", "Nescafe dolce gusto", "Jura", "Percolator"], "subtopics": ["Coffee makers", "Coffee pods", "Tea kettles"]}, {"label": "Kitchenware", "relevance": 0.6, "description": "Tools and utensils used for cooking and food preparation.", "nouns": ["Garlic crusher", "Carving knife", "Chef knife", "Butter dish with lid", "Cutting board", "Colander", "Peppermill", "Cutlery tray", "Kitchen utensils", "Chopsticks"], "subtopics": ["Knives", "Cutting boards", "Utensils"]}, {"label": "Dinnerware", "relevance": 0.5, "description": "Plates, bowls, and other dishes used for serving food.", "nouns": ["Christmas dinner set", "Platter", "Serving tray", "Rectangle plates", "Denby dinner set", "Dinnerware", "Pasta bowls", "Soup bowls", "White plate", "Plate sets"], "subtopics": ["Plates", "Bowls", "Serving dishes"]}, {"label": "Small Appliances", "relevance": 0.4, "description": "Small electric appliances used for food preparation and cooking.", "nouns": ["Breville blend active", "Sandwich maker", "Toaster", "Smoothie maker", "Air fryer", "Low fat fryer", "Multi cooker", "Pizza stone", "Bread maker", "Burger maker"], "subtopics": ["Blenders", "Toasters", "Fryers"]}, {"label": "Tableware", "relevance": 0.3, "description": "Accessories used for setting and decorating the table.", "nouns": ["Round tablecloths", "Wipe clean tablecloth", "Grey table runner", "Table runners", "Napkin", "Table cloth", "Vinyl tablecloth", "Shot glasses", "Bundt tin", "White tablecloth"], "subtopics": ["Tablecloths", "Napkins", "Table runners"]}, {"label": "Refrigeration", "relevance": 0.2, "description": "Appliances used for storing and preserving food.", "nouns": ["Smeg fridge", "Samsung American fridge freezer", "Chest freezer", "Small freezer", "Fridge freezer", "Integrated dishwasher", "Dishwasher", "Cheese grater", "Saladmaster", "Food steamer"], "subtopics": ["Refrigerators", "Freezers", "Dishwashers"]}]}