{"label": "Mobile Homes for Sale", "description": "Market category for buying and selling mobile homes.", "intents": ["Find mobile homes for permanent living.", "Buy a mobile home for vacation.", "Sell a used mobile home."], "subcategories": [{"label": "New Mobile Homes", "relevance": 0.9, "description": "Brand new mobile homes for sale.", "nouns": ["Mobile homes", "Manufactured homes"], "subtopics": ["Single-wide", "Double-wide", "Tiny homes"]}, {"label": "Used Mobile Homes", "relevance": 0.9, "description": "Pre-owned mobile homes for sale.", "nouns": ["Mobile homes", "Manufactured homes"], "subtopics": ["Single-wide", "Double-wide", "Tiny homes"]}, {"label": "Off-site Mobile Homes", "relevance": 0.8, "description": "Mobile homes for sale that are not currently sited.", "nouns": ["Mobile homes", "Manufactured homes"], "subtopics": ["Transportation", "Installation"]}, {"label": "Mobile Home Parks", "relevance": 0.7, "description": "Mobile homes for sale in parks or communities.", "nouns": ["Mobile home parks", "Manufactured home communities"], "subtopics": ["Retirement communities", "Family-friendly parks"]}, {"label": "Log Cabin Mobile Homes", "relevance": 0.6, "description": "Mobile homes that resemble log cabins.", "nouns": ["Log cabin mobile homes", "Rustic mobile homes"], "subtopics": ["Wooden interiors", "Outdoor living spaces"]}, {"label": "Park Homes", "relevance": 0.5, "description": "Mobile homes that are designed to look like traditional homes.", "nouns": ["Park homes", "Residential mobile homes"], "subtopics": ["Bungalow-style homes", "Two-story homes"]}]}