{"label": "Adventure Travel", "description": "Travel and activities that involve exploration, excitement, and risk-taking.", "intents": ["Plan an adventure trip", "Find adventure activities", "Book a safari", "Trekking and hiking", "Explore natural wonders"], "subcategories": [{"label": "Safari", "relevance": 0.9, "description": "Wildlife viewing and nature exploration in Africa.", "nouns": ["Game reserve", "Safari lodge", "Wildlife", "Big five", "Safari outfit"], "subtopics": ["Kruger National Park", "Masai Mara", "Serengeti", "Okavango Delta", "Safari and beach"]}, {"label": "Trekking and Hiking", "relevance": 0.8, "description": "Walking and hiking trips in various locations around the world.", "nouns": ["Hiking trails", "Mountain trekking", "Walking holidays", "Backpacking", "Trekking gear"], "subtopics": ["Hadrian's Wall", "Great Wall of China", "Snowdon Trek", "Mount Everest Base Camp", "Annapurna Circuit Trek"]}, {"label": "Cycling Holidays", "relevance": 0.7, "description": "Bike tours and cycling holidays in various locations around the world.", "nouns": ["Bike tours", "Cycling routes", "Mountain biking", "Road cycling", "Cycling gear"], "subtopics": ["Scotland", "France", "Italy", "Spain", "Holland"]}, {"label": "Desert Adventures", "relevance": 0.6, "description": "Trips and activities in desert environments.", "nouns": ["Desert safaris", "Sandboarding", "Camel trekking", "Desert camping", "Oases"], "subtopics": ["Sossusvlei", "Namib Desert", "Sahara", "Gobi Desert", "Atacama Desert"]}, {"label": "Water Adventures", "relevance": 0.5, "description": "Trips and activities involving water sports and activities.", "nouns": ["Rafting", "Kayaking", "Scuba diving", "Surfing", "Sailing"], "subtopics": ["White water rafting", "Scuba diving in the Great Barrier Reef", "Surfing in Hawaii", "Sailing in the Caribbean", "Kayaking in Norway"]}]}