{
    "query_audits": [
        {
            "query": "glasses drinking",
            "relevance": 0.6
        },
        {
            "query": "argos blender",
            "relevance": 0.3
        },
        {
            "query": "mini oven",
            "relevance": 0.9
        },
        {
            "query": "dual fuel cooker",
            "relevance": 0.9
        },
        {
            "query": "bombay sapphire glasses",
            "relevance": 0.7
        },
        {
            "query": "currys gas cookers",
            "relevance": 0.9
        },
        {
            "query": "cocktail set",
            "relevance": 0.4
        },
        {
            "query": "argos coffee machine",
            "relevance": 0.7
        },
        {
            "query": "cheap integrated dishwasher",
            "relevance": 0.8
        },
        {
            "query": "bathroom scales argos",
            "relevance": 0.5
        },
        {
            "query": "stemless wine glasses",
            "relevance": 0.6
        },
        {
            "query": "zanussi oven",
            "relevance": 0.9
        },
        {
            "query": "single oven",
            "relevance": 0.9
        },
        {
            "query": "gas stove",
            "relevance": 0.9
        },
        {
            "query": "decanter",
            "relevance": 0.6
        },
        {
            "query": "best slimline dishwasher",
            "relevance": 0.8
        },
        {
            "query": "gas oven and hob",
            "relevance": 0.9
        },
        {
            "query": "free standing breakfast bar",
            "relevance": 0.4
        },
        {
            "query": "dish rack",
            "relevance": 0.5
        },
        {
            "query": "digital kitchen scales",
            "relevance": 0.5
        },
        {
            "query": "hotpoint oven",
            "relevance": 0.9
        },
        {
            "query": "dolce gusto pods",
            "relevance": 0.7
        },
        {
            "query": "lamona dishwasher",
            "relevance": 0.8
        },
        {
            "query": "lacanche range",
            "relevance": 0.9
        },
        {
            "query": "salter kitchen scales",
            "relevance": 0.5
        },
        {
            "query": "plastic wine glasses",
            "relevance": 0.6
        },
        {
            "query": "argos scales",
            "relevance": 0.5
        },
        {
            "query": "bosch oven",
            "relevance": 0.9
        },
        {
            "query": "initial mugs",
            "relevance": 0.6
        },
        {
            "query": "range cooker sale",
            "relevance": 0.9
        },
        {
            "query": "ice crush",
            "relevance": 0.4
        },
        {
            "query": "tesco mugs",
            "relevance": 0.6
        },
        {
            "query": "electric hob and oven",
            "relevance": 0.9
        },
        {
            "query": "dual fuel range",
            "relevance": 0.9
        },
        {
            "query": "riedel wine glasses",
            "relevance": 0.6
        },
        {
            "query": "hotpoint slimline dishwasher",
            "relevance": 0.8
        },
        {
            "query": "dishwasher slimline",
            "relevance": 0.8
        },
        {
            "query": "oven",
            "relevance": 0.9
        },
        {
            "query": "new world oven",
            "relevance": 0.9
        },
        {
            "query": "tassimo vivy",
            "relevance": 0.7
        },
        {
            "query": "built under oven",
            "relevance": 0.9
        },
        {
            "query": "cheap range cookers",
            "relevance": 0.9
        },
        {
            "query": "vitamix",
            "relevance": 0.4
        },
        {
            "query": "range cookers 90cm",
            "relevance": 0.9
        },
        {
            "query": "delonghi coffee machine",
            "relevance": 0.7
        },
        {
            "query": "beko slimline dishwasher",
            "relevance": 0.8
        },
        {
            "query": "lamona oven",
            "relevance": 0.9
        },
        {
            "query": "tesco gas cookers",
            "relevance": 0.9
        },
        {
            "query": "cooking gas",
            "relevance": 0.9
        },
        {
            "query": "wine bottle opener",
            "relevance": 0.6
        },
        {
            "query": "aeg hob",
            "relevance": 0.9
        },
        {
            "query": "thermal mug",
            "relevance": 0.5
        },
        {
            "query": "currys built in ovens",
            "relevance": 0.9
        },
        {
            "query": "personalised whisky glass",
            "relevance": 0.6
        },
        {
            "query": "gin glasses",
            "relevance": 0.6
        },
        {
            "query": "travel cup",
            "relevance": 0.5
        },
        {
            "query": "bosch coffee machine",
            "relevance": 0.7
        },
        {
            "query": "design your own mug",
            "relevance": 0.6
        },
        {
            "query": "wine stoppers",
            "relevance": 0.6
        },
        {
            "query": "baccarat",
            "relevance": 0.6
        },
        {
            "query": "new world gas cookers",
            "relevance": 0.9
        },
        {
            "query": "neff gas hobs",
            "relevance": 0.9
        },
        {
            "query": "indesit cooker",
            "relevance": 0.9
        },
        {
            "query": "currys dishwashers",
            "relevance": 0.8
        },
        {
            "query": "delonghi espresso",
            "relevance": 0.7
        },
        {
            "query": "rangemaster classic 90",
            "relevance": 0.9
        },
        {
            "query": "stainless steel dishwasher",
            "relevance": 0.8
        },
        {
            "query": "beko dishwasher",
            "relevance": 0.8
        },
        {
            "query": "currys ovens",
            "relevance": 0.9
        },
        {
            "query": "nespresso lattissima touch",
            "relevance": 0.7
        },
        {
            "query": "aeg dishwasher",
            "relevance": 0.8
        },
        {
            "query": "miele dishwasher",
            "relevance": 0.8
        },
        {
            "query": "plastic cocktail glasses",
            "relevance": 0.6
        },
        {
            "query": "costa coffee machine",
            "relevance": 0.7
        },
        {
            "query": "personalised glasses",
            "relevance": 0.6
        },
        {
            "query": "stoves cookers",
            "relevance": 0.9
        },
        {
            "query": "table top oven",
            "relevance": 0.9
        },
        {
            "query": "cheap dishwashers",
            "relevance": 0.8
        },
        {
            "query": "mr frosty ice cream maker",
            "relevance": 0.4
        },
        {
            "query": "delonghi",
            "relevance": 0.4
        },
        {
            "query": "wood fired pizza oven",
            "relevance": 0.9
        },
        {
            "query": "customised mugs",
            "relevance": 0.6
        },
        {
            "query": "krups nespresso",
            "relevance": 0.7
        },
        {
            "query": "smeg cookers",
            "relevance": 0.9
        },
        {
            "query": "electric freestanding cooker",
            "relevance": 0.9
        },
        {
            "query": "stove oven",
            "relevance": 0.9
        },
        {
            "query": "ninja bullet",
            "relevance": 0.4
        },
        {
            "query": "coffee travel mugs",
            "relevance": 0.5
        },
        {
            "query": "portable gas stove",
            "relevance": 0.9
        },
        {
            "query": "flavel cooker",
            "relevance": 0.9
        },
        {
            "query": "aeroccino",
            "relevance": 0.7
        },
        {
            "query": "travel mugs uk",
            "relevance": 0.5
        },
        {
            "query": "electric double oven",
            "relevance": 0.9
        },
        {
            "query": "double gas oven",
            "relevance": 0.9
        },
        {
            "query": "ikea breakfast bar",
            "relevance": 0.4
        },
        {
            "query": "currys cookers gas",
            "relevance": 0.9
        },
        {
            "query": "aeg double oven",
            "relevance": 0.9
        },
        {
            "query": "neff slide and hide",
            "relevance": 0.9
        },
        {
            "query": "interlevin",
            "relevance": 0.4
        },
        {
            "query": "freestanding dishwasher",
            "relevance": 0.8
        }
    ]
}