{"query_audits": [{"query": "wedding fairs sussex", "relevance": 0.8}, {"query": "framptons number plates", "relevance": 0.7}, {"query": "dvla personal number plates", "relevance": 0.7}, {"query": "tickets for chelsea flower show", "relevance": 0.6}, {"query": "number plate stickers halfords", "relevance": 0.7}, {"query": "exhibition ideas", "relevance": 0.7}, {"query": "wedding fairs south wales", "relevance": 0.8}, {"query": "craft exhibition", "relevance": 0.5}, {"query": "large format display", "relevance": 0.7}, {"query": "trade show displays", "relevance": 0.7}]}