{"query_audits": [{"query": "dab car radio adapter", "relevance": 0.5}, {"query": "pioneer appradio 4", "relevance": 0.9}, {"query": "fli subwoofer", "relevance": 0.8}, {"query": "cb radios for sale", "relevance": 0.0}, {"query": "sony cd player", "relevance": 0.5}, {"query": "car radio installation near me", "relevance": 1.0}, {"query": "pioneer avh x3700dab", "relevance": 0.9}, {"query": "airband radio", "relevance": 0.0}, {"query": "quad lock", "relevance": 0.0}, {"query": "double din head unit", "relevance": 0.9}]}