{"query_audits": [{"query": "fitband", "relevance": 0.0}, {"query": "retreats uk", "relevance": 0.0}, {"query": "muscle mousse", "relevance": 0.7}, {"query": "weight lifting trainers", "relevance": 0.7}, {"query": "vibration plate exercises", "relevance": 0.8}, {"query": "ab machines", "relevance": 0.5}, {"query": "wobble cushion", "relevance": 0.6}, {"query": "bike trainer", "relevance": 0.8}, {"query": "flabelos", "relevance": 0.0}, {"query": "gyms in bedford", "relevance": 0.3}, {"query": "yoga 300", "relevance": 0.6}, {"query": "gym maidenhead", "relevance": 0.3}, {"query": "cheap gym memberships near me", "relevance": 0.3}, {"query": "back rolls", "relevance": 0.0}, {"query": "best fitness band", "relevance": 0.0}, {"query": "best rowing machine", "relevance": 0.8}, {"query": "8ft trampoline", "relevance": 0.6}, {"query": "5kg dumbbells", "relevance": 0.7}, {"query": "manual treadmill", "relevance": 0.8}, {"query": "gyms in reading", "relevance": 0.3}, {"query": "personal trainer liverpool", "relevance": 0.3}, {"query": "power block", "relevance": 0.7}, {"query": "gyms in bournemouth", "relevance": 0.3}, {"query": "lincoln gym", "relevance": 0.3}, {"query": "dumbbell weights", "relevance": 0.7}, {"query": "treadmill sale", "relevance": 0.8}, {"query": "exercise bike for sale", "relevance": 0.8}, {"query": "direct drive turbo trainer", "relevance": 0.8}, {"query": "running machine", "relevance": 0.8}, {"query": "rowing machines uk", "relevance": 0.8}, {"query": "slendertone belt", "relevance": 0.5}, {"query": "gyms in nottingham", "relevance": 0.3}, {"query": "kaged muscle", "relevance": 0.7}, {"query": "cheap gyms near me", "relevance": 0.3}, {"query": "cross trainer", "relevance": 0.8}, {"query": "yoga at home", "relevance": 0.6}, {"query": "best exercise bike", "relevance": 0.8}, {"query": "pay as you go gym near me", "relevance": 0.3}, {"query": "exercise bike", "relevance": 0.8}, {"query": "gymnastic crash mats", "relevance": 0.5}, {"query": "wahoo kickr", "relevance": 0.8}, {"query": "argos skipping rope", "relevance": 0.5}, {"query": "ifit", "relevance": 0.0}, {"query": "jawbone up", "relevance": 0.0}, {"query": "home exercises", "relevance": 0.6}, {"query": "pro fitness treadmill", "relevance": 0.8}, {"query": "cycleops fluid 2", "relevance": 0.8}, {"query": "20kg kettlebell", "relevance": 0.7}, {"query": "reebok treadmill", "relevance": 0.8}, {"query": "roller trainers", "relevance": 0.8}, {"query": "muscle gain", "relevance": 0.7}, {"query": "weight bench argos", "relevance": 0.7}, {"query": "pull up mate", "relevance": 0.7}, {"query": "pilates classes near me", "relevance": 0.6}, {"query": "best yoga dvd", "relevance": 0.6}, {"query": "bowflex", "relevance": 0.7}, {"query": "argos gym ball", "relevance": 0.5}, {"query": "rogue fitness uk", "relevance": 0.7}, {"query": "slendertone abs", "relevance": 0.5}, {"query": "rower", "relevance": 0.8}, {"query": "hand exercises", "relevance": 0.6}, {"query": "powerplate", "relevance": 0.8}, {"query": "acton gym", "relevance": 0.3}, {"query": "resistance bands", "relevance": 0.6}, {"query": "resistance tube", "relevance": 0.6}, {"query": "insanity max 30", "relevance": 0.6}, {"query": "simply gym swindon", "relevance": 0.3}, {"query": "body by vi", "relevance": 0.0}, {"query": "rebounder trampoline", "relevance": 0.6}, {"query": "gym norwich", "relevance": 0.3}, {"query": "gym ealing", "relevance": 0.3}, {"query": "home gym ideas", "relevance": 0.7}, {"query": "skierg", "relevance": 0.8}, {"query": "fitness program", "relevance": 0.6}, {"query": "muscle top", "relevance": 0.7}, {"query": "versaclimber", "relevance": 0.8}, {"query": "hex dumbbells", "relevance": 0.7}, {"query": "balance cushion", "relevance": 0.6}, {"query": "concept 2", "relevance": 0.8}, {"query": "foam roller", "relevance": 0.6}, {"query": "pull up bar", "relevance": 0.7}, {"query": "balance ball", "relevance": 0.6}, {"query": "pilates mat", "relevance": 0.6}, {"query": "gyms in portsmouth", "relevance": 0.3}, {"query": "stringer vest", "relevance": 0.5}, {"query": "cheap rowing machine", "relevance": 0.8}, {"query": "reebok zr10 treadmill", "relevance": 0.8}, {"query": "mini exercise bike", "relevance": 0.8}, {"query": "barbell", "relevance": 0.7}, {"query": "rowing machine argos", "relevance": 0.8}, {"query": "dumbbells for sale", "relevance": 0.7}, {"query": "wolverson kettlebells", "relevance": 0.7}, {"query": "weight plates", "relevance": 0.7}, {"query": "life fitness treadmill", "relevance": 0.8}, {"query": "six pack abs", "relevance": 0.5}, {"query": "wobble board exercises", "relevance": 0.6}, {"query": "gymnastics mats for home", "relevance": 0.5}, {"query": "carl lewis treadmill", "relevance": 0.8}, {"query": "york multi gym", "relevance": 0.7}, {"query": "vibrapower slim", "relevance": 0.8}]}