{"query_audits": [{"query": "valid planning objections uk", "relevance": 0.6}, {"query": "kontrol s8", "relevance": 0.0}, {"query": "top planning consultants uk", "relevance": 0.9}, {"query": "planning application consultants", "relevance": 0.9}, {"query": "sustainability policy uk", "relevance": 0.7}, {"query": "planning application appeal process", "relevance": 0.8}, {"query": "planning consultants oxfordshire", "relevance": 0.9}, {"query": "block plans for planning permission", "relevance": 0.8}, {"query": "planning consultants milton keynes", "relevance": 0.9}, {"query": "planning enforcement notice", "relevance": 0.6}]}