{"query_audits": [{"query": "pedicure aberdeen", "relevance": 0.8}, {"query": "spas in maidstone", "relevance": 0.6}, {"query": "spa in east london", "relevance": 0.6}, {"query": "milton keynes spa", "relevance": 0.6}, {"query": "foil nails", "relevance": 0.0}, {"query": "gel nails newcastle", "relevance": 0.8}, {"query": "pedicure offers", "relevance": 0.8}, {"query": "shellac nails leeds", "relevance": 0.8}, {"query": "gel nail removal", "relevance": 0.8}, {"query": "croydon cosmetic clinic", "relevance": 0.0}]}