{"query_audits": [{"query": "powakaddy bag", "relevance": 0.7}, {"query": "taylormade driver", "relevance": 0.9}, {"query": "golf trousers uk", "relevance": 0.8}, {"query": "toilet golf", "relevance": 0.0}, {"query": "golf insurance", "relevance": 0.6}, {"query": "golf gloves uk", "relevance": 0.8}, {"query": "ecco golf shoes", "relevance": 0.8}, {"query": "motocaddy lithium battery", "relevance": 0.7}, {"query": "cheap golf clothing", "relevance": 0.8}, {"query": "american golf stores", "relevance": 0.6}]}