{"query_audits": [{"query": "where to holiday in march", "relevance": 0.9}, {"query": "days out in sussex for couples", "relevance": 0.7}, {"query": "where to eat in dubai", "relevance": 0.8}, {"query": "awesome stuff to buy", "relevance": 0.0}, {"query": "what to do in antigua", "relevance": 0.9}, {"query": "days out in staffordshire for adults", "relevance": 0.7}, {"query": "best places in gran canaria", "relevance": 0.9}, {"query": "days out in east sussex", "relevance": 0.7}, {"query": "best area to stay in dubai", "relevance": 0.9}, {"query": "fun days out for kids", "relevance": 0.7}]}