{"query_audits": [{"query": "water tank in loft", "relevance": 0.1}, {"query": "hydroponic kit", "relevance": 0.8}, {"query": "indian ornamental", "relevance": 0.0}, {"query": "fish farming uk", "relevance": 0.4}, {"query": "large water tanks", "relevance": 0.1}, {"query": "oyster 1 colour pack", "relevance": 0.3}, {"query": "carp syndicates sussex", "relevance": 0.6}, {"query": "marine phosphate remover", "relevance": 0.7}, {"query": "oyster max 2", "relevance": 0.3}, {"query": "stealth grow box", "relevance": 0.2}]}