{"query_audits": [{"query": "usain bolt kit", "relevance": 0.2}, {"query": "javelins for sale 600g", "relevance": 0.7}, {"query": "telegan sprint v2", "relevance": 0.0}, {"query": "loop cross s1 sale", "relevance": 0.0}, {"query": "santa run medals", "relevance": 0.0}, {"query": "track starting blocks", "relevance": 0.6}, {"query": "swim bike run brownlee", "relevance": 0.0}, {"query": "track button", "relevance": 0.0}, {"query": "santa monica track club shirt", "relevance": 0.0}, {"query": "track equipment", "relevance": 0.8}]}