{"query_audits": [{"query": "out of control teenager legal options", "relevance": 0.7}, {"query": "boys age 8", "relevance": 0.0}, {"query": "under 18 dating website", "relevance": 0.6}, {"query": "teenage daughter depression", "relevance": 0.8}, {"query": "relationship advice for teens", "relevance": 1.0}, {"query": "john lewis teenager", "relevance": 0.0}, {"query": "asperger's syndrome in teenage years", "relevance": 0.8}, {"query": "teenager shaving", "relevance": 0.0}, {"query": "girls age 10", "relevance": 0.0}, {"query": "bedwetting age 6", "relevance": 0.0}]}