{"query_audits": [{"query": "venetian art", "relevance": 0.5}, {"query": "antique monks bench", "relevance": 0.8}, {"query": "coach house lamps", "relevance": 0.0}, {"query": "1930s wardrobe", "relevance": 0.6}, {"query": "french antique mirror", "relevance": 0.8}, {"query": "welsh dresser shabby chic", "relevance": 0.7}, {"query": "french grey bedroom", "relevance": 0.8}, {"query": "french grey dining chairs", "relevance": 0.6}, {"query": "the french bed company", "relevance": 0.8}, {"query": "period furniture", "relevance": 0.7}]}