{"query_audits": [{"query": "evohome honeywell", "relevance": 0.8}, {"query": "google thermostat", "relevance": 0.0}, {"query": "honeywell hcw80", "relevance": 0.8}, {"query": "drayton thermostat manual", "relevance": 0.7}, {"query": "hive heating", "relevance": 0.5}, {"query": "wireless radiator thermostat", "relevance": 0.8}, {"query": "sangamo time clock", "relevance": 0.0}, {"query": "horstmann heating controls", "relevance": 0.5}, {"query": "free nest thermostat", "relevance": 0.0}, {"query": "wireless boiler thermostat", "relevance": 0.8}]}